dagrad/__init__.py
dagrad/daglearner.py
dagrad/hfunction/__init__.py
dagrad/hfunction/h_functions.py
dagrad/method/__init__.py
dagrad/method/dagma.py
dagrad/method/notears.py
dagrad/method/topo.py
dagrad/optimizer/__init__.py
dagrad/optimizer/optimizer.py
dagrad/score/__init__.py
dagrad/score/score.py
dagrad/utils/NNstructure.py
dagrad/utils/__init__.py
dagrad/utils/configure.py
dagrad/utils/general_utils.py
dagrad/utils/profiler.py
dagrad/utils/topo_utils.py
dagrad/utils/utils.py
examples/__init__.py
examples/example.py
tests/TestDAGMA.py
tests/TestNOTEARS.py
tests/TestTOPO.py
tests/__init__.py
tests/benchmarking.py
tests/benchmarking_job_runner.py
tests/benchmarking_method_runner.py
tests/hyperparameter_tuning_job.py
tests/hyperparameter_tuning_method.py
tests/plot.py
tests/summarize_data.py
tests/test.py
tests/testDiscrete.py
tests/test_cdt.py
dagrad-0.0.1.dist-info/LICENSE
dagrad-0.0.1.dist-info/METADATA
dagrad-0.0.1.dist-info/WHEEL
dagrad-0.0.1.dist-info/top_level.txt
dagrad-0.0.1.dist-info/RECORD
