Metadata-Version: 2.1
Name: dagrad
Version: 0.0.1
Summary: A project for DAG learning
Home-page: https://github.com/Duntrain/DAGlearner
Author: Chang Deng
Author-email: changdeng@uchicago.edu
License: MIT
Project-URL: Homepage, https://github.com/Duntrain/DAGlearner
Project-URL: Documentation, https://readthedocs.org
Project-URL: Repository, https://github.com/Duntrain/DAGlearner
Project-URL: Issues, https://github.com/Duntrain/DAGlearner/issues
Keywords: dagma,notears,topo,causal discovery,bayesian network,structure learning
Classifier: Development Status :: 3 - Alpha
Classifier: Intended Audience :: Developers
Classifier: License :: OSI Approved :: MIT License
Classifier: Programming Language :: Python :: 3
Classifier: Programming Language :: Python :: 3.7
Classifier: Topic :: Scientific/Engineering :: Artificial Intelligence
Classifier: Topic :: Scientific/Engineering :: Mathematics
Requires-Python: >=3.7
License-File: LICENSE
Requires-Dist: numpy
Requires-Dist: dagma
Requires-Dist: scipy
Requires-Dist: python-igraph
Requires-Dist: torch
Requires-Dist: scikit-learn
